MANIFEST.in
README.markdown
setup.py
examples/example.py
examples/example_ME5ME6.py
substratestack/__init__.py
substratestack/version.py
substratestack.egg-info/PKG-INFO
substratestack.egg-info/SOURCES.txt
substratestack.egg-info/dependency_links.txt
substratestack.egg-info/top_level.txt