Metadata-Version: 1.1
Name: substratestack
Version: 0.3
Summary: Python package to simplify substrate stackups and export them for use in Momentum and Sonnet
Home-page: http://github.com/bmachiel/python-substratestack
Author: Brecht Machiels
Author-email: brecht.machiels@esat.kuleuven.be
License: BSD (2-clause)
Keywords: substrate stack ADS Momentum Sonnet em
Platform: UNKNOWN
Classifier: Development Status :: 3 - Alpha
Classifier: Intended Audience :: Science/Research
Classifier: License :: OSI Approved :: BSD License
Classifier: Operating System :: OS Independent
Classifier: Programming Language :: Python
Classifier: Topic :: Scientific/Engineering :: Electronic Design Automation (EDA)
Classifier: Topic :: Software Development :: Libraries :: Python Modules
Requires: reportlab
Provides: substratestack
